slackflow/__init__.py
slackflow/airflow.py
slackflow/constants.py
slackflow/models.py
slackflow/slack.py
slackflow-1.0.0.data/scripts/slackflow-run
slackflow-1.0.0.dist-info/DESCRIPTION.rst
slackflow-1.0.0.dist-info/METADATA
slackflow-1.0.0.dist-info/RECORD
slackflow-1.0.0.dist-info/WHEEL
slackflow-1.0.0.dist-info/metadata.json
slackflow-1.0.0.dist-info/top_level.txt
