Metadata-Version: 2.0
Name: slackflow
Version: 1.0.0
Summary: Slack notifications for airflow dags.
Home-page: https://github.com/kbeauregard/slackflow
Author: Kyle Beauregard
Author-email: kylembeauregard@gmail.com
License: UNKNOWN
Keywords: slack,airflow
Platform: UNKNOWN
Classifier: Programming Language :: Python :: 3
Classifier: Programming Language :: Python :: 3.7
Classifier: Operating System :: OS Independent
Requires-Dist: pymongo (==3.9.0)
Requires-Dist: requests (>=2.23.0)
Requires-Dist: slackclient (>=2.7.2)
